Metadata-Version: 2.1
Name: asdfghjkl
Version: 0.1a5
Summary: ASDL: Automatic Second-order Differentiation (for Fisher, Gradient covariance, Hessian, Jacobian, and Kernel) Library
Home-page: https://github.com/kazukiosawa/asdl
Author: Kazuki Osawa
Author-email: osawa1021@gmail.com
Project-URL: Bug Tracker, https://github.com/kazukiosawa/asdl/issues
Classifier: Programming Language :: Python :: 3
Classifier: License :: OSI Approved :: MIT License
Classifier: Operating System :: OS Independent
Requires-Python: >=3.7
License-File: LICENSE
Requires-Dist: torch>=1.13.0
Requires-Dist: numpy
